{
    "action": [
        {
            "action_type": "CALL_TRIGGER_FUNC", 
            "args_list": [
                {
                    "arg_type": 100177, 
                    "args_list": [
                        {
                            "arg_type": 100009, 
                            "args_list": [
                                10019
                            ], 
                            "sub_type": 1
                        }, 
                        {
                            "arg_type": 100002, 
                            "args_list": [
                                1
                            ], 
                            "sub_type": 1
                        }
                    ], 
                    "op_arg": [], 
                    "op_arg_enable": [], 
                    "sub_type": "657e172e718711eebc0e30d042e90e85"
                }
            ], 
            "bp": false, 
            "call_rt_arg_idxes": [], 
            "element_id": 873562148000032, 
            "enable": true
        }, 
        {
            "action_type": "SOUND_CONTROL", 
            "args_list": [
                {
                    "arg_type": 100025, 
                    "args_list": [
                        1
                    ], 
                    "sub_type": 1
                }, 
                {
                    "arg_type": 100214, 
                    "args_list": [
                        {
                            "__tuple__": true, 
                            "items": [
                                "SOUND_ENTITY", 
                                "BGM"
                            ]
                        }
                    ], 
                    "sub_type": 2
                }, 
                {
                    "arg_type": 100316, 
                    "args_list": [
                        0
                    ], 
                    "sub_type": 1
                }
            ], 
            "bp": false, 
            "element_id": 487686177949340, 
            "enable": true
        }, 
        {
            "action_type": "SET_VARIABLE", 
            "args_list": [
                {
                    "arg_type": 100030, 
                    "args_list": [
                        {
                            "__tuple__": true, 
                            "items": [
                                "SOUND_ENTITY", 
                                "\u6218\u6597\u97f3\u65481"
                            ]
                        }
                    ], 
                    "sub_type": 1
                }, 
                {
                    "arg_type": 100214, 
                    "args_list": [
                        {
                            "arg_type": 100025, 
                            "args_list": [
                                1
                            ], 
                            "sub_type": 1
                        }, 
                        {
                            "arg_type": 100084, 
                            "args_list": [
                                134246902
                            ], 
                            "sub_type": 1
                        }, 
                        {
                            "arg_type": 100001, 
                            "args_list": [
                                true
                            ], 
                            "sub_type": 1
                        }
                    ], 
                    "op_arg": [
                        null, 
                        null
                    ], 
                    "op_arg_enable": [
                        false, 
                        false
                    ], 
                    "sub_type": "PLAY_SOUND_FOR_PLAYER"
                }
            ], 
            "bp": false, 
            "element_id": 873562148000046, 
            "enable": true
        }
    ], 
    "call_enabled": true, 
    "condition": [], 
    "enabled": true, 
    "event": [
        {
            "args_list": [
                {
                    "arg_type": 100006, 
                    "args_list": [
                        7
                    ], 
                    "sub_type": 1
                }, 
                {
                    "arg_type": 100044, 
                    "args_list": [
                        1
                    ], 
                    "sub_type": 1
                }, 
                {
                    "arg_type": 100009, 
                    "args_list": [
                        10019
                    ], 
                    "sub_type": 1
                }
            ], 
            "element_id": 873562148000001, 
            "enable": true, 
            "event_type": "UNIT_REGION_EVENT"
        }
    ], 
    "group_id": 0, 
    "p_trigger_id": null, 
    "trigger_id": 873562148, 
    "trigger_name": "\u8fdb\u5165\u533a\u57df\u6218\u65971", 
    "valid": true
}